teams_channel/__init__.py
teams_channel/example.py
teams_channel/scripts.py
teams_channel/send_message_to_teams.py
teams_channel-0.0.1.dist-info/METADATA
teams_channel-0.0.1.dist-info/WHEEL
teams_channel-0.0.1.dist-info/entry_points.txt
teams_channel-0.0.1.dist-info/top_level.txt
teams_channel-0.0.1.dist-info/RECORD
